loafer/__init__.py
loafer/dispatchers.py
loafer/exceptions.py
loafer/ext/__init__.py
loafer/ext/sentry.py
loafer/managers.py
loafer/message_translators.py
loafer/providers.py
loafer/routes.py
loafer/runners.py
loafer/utils.py
pydrinker_loafer-1.0.1.dist-info/LICENSE
pydrinker_loafer-1.0.1.dist-info/WHEEL
pydrinker_loafer-1.0.1.dist-info/METADATA
pydrinker_loafer-1.0.1.dist-info/RECORD
