Metadata-Version: 2.1
Name: pydrinker-loafer
Version: 1.0.1
Summary: Asynchronous message dispatcher for concurrent tasks processing
Home-page: https://github.com/pydrinker/pydrinker-loafer/
License: MIT
Keywords: asyncio,message,dispatcher,tasks,microservices
Author: Rafael Henrique da Silva Correia
Author-email: rafael@abraseucodigo.com.br
Requires-Python: >=3.7,<3.10
Classifier: Development Status :: 5 - Production/Stable
Classifier: Environment :: Console
Classifier: Intended Audience :: Developers
Classifier: License :: OSI Approved :: MIT License
Classifier: Natural Language :: English
Classifier: Operating System :: OS Independent
Classifier: Programming Language :: Python :: 3
Classifier: Programming Language :: Python :: 3 :: Only
Classifier: Programming Language :: Python :: 3.7
Classifier: Programming Language :: Python :: 3.8
Classifier: Programming Language :: Python :: 3.9
Classifier: Topic :: System :: Distributed Computing
Requires-Dist: cached-property (>=1.5.2,<2.0.0)
Project-URL: Download, https://github.com/pydrinker/pydrinker-loafer/releases
Project-URL: Repository, https://github.com/pydrinker/pydrinker-loafer/
